litestar_workflows/__init__.py
litestar_workflows/__metadata__.py
litestar_workflows-0.1.0.dist-info/METADATA
litestar_workflows-0.1.0.dist-info/WHEEL
litestar_workflows-0.1.0.dist-info/licenses/LICENSE
litestar_workflows-0.1.0.dist-info/RECORD
