Metadata-Version: 2.3
Name: litestar-workflows
Version: 0.1.0
Summary: Workflow management in Litestar
Project-URL: Changelog, https://github.com/JacobCoffee/litestar-workflows/releases/
Project-URL: Discord, https://discord.gg/litestar-919193495116337154
Project-URL: Documentation, https://jacobcoffee.github.io/litestar-workflows
Project-URL: Issue Tracker, https://github.com/JacobCoffee/litestar-workflows/issues
Project-URL: Reddit, https://www.reddit.com/r/LitestarAPI
Project-URL: Repository, https://github.com/JacobCoffee/litestar-workflows
Project-URL: Twitter, https://twitter.com/_scriptr
Author-email: Jacob Coffee <jacob@z7x.org>
License: MIT
License-File: LICENSE
Keywords: approvals,litestar,workflows
Requires-Python: >=3.9
Requires-Dist: litestar>=2
Requires-Dist: rich-click>=1.7.4
Provides-Extra: db
Requires-Dist: litestar[sqlalchemy]; extra == 'db'
Provides-Extra: dev-lint
Requires-Dist: blacken-docs>=1.16.0; extra == 'dev-lint'
Requires-Dist: codespell>=2.2.6; extra == 'dev-lint'
Requires-Dist: mypy>=1.9.0; extra == 'dev-lint'
Requires-Dist: pre-commit>=3.6.2; extra == 'dev-lint'
Requires-Dist: pyright>=1.1.355; extra == 'dev-lint'
Requires-Dist: ruff>=0.3.4; extra == 'dev-lint'
Requires-Dist: sourcery>=1.16.0; extra == 'dev-lint'
Provides-Extra: dev-test
Requires-Dist: pytest-asyncio>=0.23.6; extra == 'dev-test'
Requires-Dist: pytest-cov>=4.1.0; extra == 'dev-test'
Requires-Dist: pytest>=8.1.1; extra == 'dev-test'
Provides-Extra: ui
Requires-Dist: litestar[jinja]; extra == 'ui'
